{
  "dataset": "faced",
  "task_mode": "9-class",
  "completed_at": "2026-04-01T09:36:54.232961",
  "n_folds_run": 10,
  "mean": {
    "train_loss": 0.8119,
    "val_acc": 0.549,
    "val_bal_acc": 0.5503,
    "val_auroc": 0.8669,
    "val_f1": 0.5483
  },
  "std": {
    "train_loss": 0.1681,
    "val_acc": 0.037,
    "val_bal_acc": 0.0373,
    "val_auroc": 0.0289,
    "val_f1": 0.0362
  },
  "folds": [
    {
      "fold": 1,
      "train_loss": 0.7558335332521077,
      "val_loss": 1.2844146538130092,
      "val_acc": 0.5998168498168498,
      "val_bal_acc": 0.6018518518518519,
      "val_auroc": 0.89308815472277,
      "val_f1": 0.5963448307461848,
      "best_epoch": 47,
      "lp_epochs_trained": 20,
      "ft_epochs_trained": 67,
      "lp_train_loss": 1.3792613742680384,
      "lp_val_acc": 0.532967032967033
    },
    {
      "fold": 2,
      "train_loss": 0.6875660951281416,
      "val_loss": 1.2738796356833462,
      "val_acc": 0.5989010989010989,
      "val_bal_acc": 0.5992402659069326,
      "val_auroc": 0.8930876372756715,
      "val_f1": 0.5994700558166787,
      "best_epoch": 67,
      "lp_epochs_trained": 20,
      "ft_epochs_trained": 87,
      "lp_train_loss": 1.3196926608167845,
      "lp_val_acc": 0.4908424908424908
    },
    {
      "fold": 3,
      "train_loss": 0.7348373928974414,
      "val_loss": 2.030388592363714,
      "val_acc": 0.48717948717948717,
      "val_bal_acc": 0.49097815764482433,
      "val_auroc": 0.8294864794116931,
      "val_f1": 0.48809672205300686,
      "best_epoch": 47,
      "lp_epochs_trained": 20,
      "ft_epochs_trained": 67,
      "lp_train_loss": 1.4243687857841623,
      "lp_val_acc": 0.4258241758241758
    },
    {
      "fold": 4,
      "train_loss": 0.7400347945624834,
      "val_loss": 1.3434302598711043,
      "val_acc": 0.5496031746031746,
      "val_bal_acc": 0.54809670781893,
      "val_auroc": 0.8814873042409693,
      "val_f1": 0.5518777560728982,
      "best_epoch": 57,
      "lp_epochs_trained": 20,
      "ft_epochs_trained": 77,
      "lp_train_loss": 1.3735406704961437,
      "lp_val_acc": 0.47023809523809523
    },
    {
      "fold": 5,
      "train_loss": 0.7708112278519428,
      "val_loss": 1.4087083453223819,
      "val_acc": 0.5396825396825397,
      "val_bal_acc": 0.5370370370370371,
      "val_auroc": 0.8696479909693644,
      "val_f1": 0.5419710171442992,
      "best_epoch": 56,
      "lp_epochs_trained": 20,
      "ft_epochs_trained": 76,
      "lp_train_loss": 1.461323136336183,
      "lp_val_acc": 0.4623015873015873
    },
    {
      "fold": 6,
      "train_loss": 0.7536678578551501,
      "val_loss": 1.333483614618816,
      "val_acc": 0.5744047619047619,
      "val_bal_acc": 0.5784465020576132,
      "val_auroc": 0.8833231881572932,
      "val_f1": 0.574091052479393,
      "best_epoch": 49,
      "lp_epochs_trained": 20,
      "ft_epochs_trained": 69,
      "lp_train_loss": 1.4119019673703468,
      "lp_val_acc": 0.5188492063492064
    },
    {
      "fold": 7,
      "train_loss": 1.2687770151724553,
      "val_loss": 1.528465921916659,
      "val_acc": 0.5347222222222222,
      "val_bal_acc": 0.5383230452674898,
      "val_auroc": 0.8582031607224508,
      "val_f1": 0.5319069495790093,
      "best_epoch": 1,
      "lp_epochs_trained": 20,
      "ft_epochs_trained": 21,
      "lp_train_loss": 1.4532748892495078,
      "lp_val_acc": 0.5158730158730159
    },
    {
      "fold": 8,
      "train_loss": 0.7569289791257414,
      "val_loss": 1.4257138702604506,
      "val_acc": 0.5307539682539683,
      "val_bal_acc": 0.5257201646090536,
      "val_auroc": 0.8686179340992227,
      "val_f1": 0.5298692427651953,
      "best_epoch": 42,
      "lp_epochs_trained": 20,
      "ft_epochs_trained": 62,
      "lp_train_loss": 1.3993128258479786,
      "lp_val_acc": 0.498015873015873
    },
    {
      "fold": 9,
      "train_loss": 0.764383003932156,
      "val_loss": 4.469766465444414,
      "val_acc": 0.5069444444444444,
      "val_bal_acc": 0.5095164609053497,
      "val_auroc": 0.8052929598193872,
      "val_f1": 0.5066955542182471,
      "best_epoch": 58,
      "lp_epochs_trained": 20,
      "ft_epochs_trained": 78,
      "lp_train_loss": 1.1746387504143259,
      "lp_val_acc": 0.44742063492063494
    },
    {
      "fold": 10,
      "train_loss": 0.8859621736488931,
      "val_loss": 1.3530705618479895,
      "val_acc": 0.5684523809523809,
      "val_bal_acc": 0.5735596707818931,
      "val_auroc": 0.8863150505829904,
      "val_f1": 0.5622830909378276,
      "best_epoch": 33,
      "lp_epochs_trained": 20,
      "ft_epochs_trained": 53,
      "lp_train_loss": 1.4311643963399,
      "lp_val_acc": 0.5089285714285714
    }
  ],
  "approach": "ft_lora",
  "lora_rank": 16
}