{
  "dataset": "faced",
  "task_mode": "binary",
  "completed_at": "2026-04-29T08:35:16.633399",
  "n_folds_run": 10,
  "mean": {
    "train_loss": 2.7522,
    "val_acc": 0.7648,
    "val_bal_acc": 0.7648,
    "val_auroc": 0.8305,
    "val_f1": 0.7641
  },
  "std": {
    "train_loss": 0.1299,
    "val_acc": 0.0316,
    "val_bal_acc": 0.0316,
    "val_auroc": 0.0345,
    "val_f1": 0.0317
  },
  "folds": [
    {
      "fold": 1,
      "train_loss": 2.813402606594947,
      "val_loss": 0.8244959452213385,
      "val_acc": 0.7767094017094017,
      "val_bal_acc": 0.7767094017094017,
      "val_auroc": 0.8502401563298999,
      "val_f1": 0.7751073454771197,
      "best_epoch": 23,
      "lp_epochs_trained": 16,
      "ft_epochs_trained": 43,
      "lp_train_loss": 10.242784288621717,
      "lp_val_acc": 0.6976495726495726
    },
    {
      "fold": 2,
      "train_loss": 2.705003176966021,
      "val_loss": 1.577474866157923,
      "val_acc": 0.7852564102564102,
      "val_bal_acc": 0.7852564102564102,
      "val_auroc": 0.8585520308276718,
      "val_f1": 0.7848829431438128,
      "best_epoch": 52,
      "lp_epochs_trained": 20,
      "ft_epochs_trained": 72,
      "lp_train_loss": 1.7768313846280497,
      "lp_val_acc": 0.6816239316239316
    },
    {
      "fold": 3,
      "train_loss": 2.773076449671099,
      "val_loss": 2.0765379718226247,
      "val_acc": 0.7286324786324786,
      "val_bal_acc": 0.7286324786324787,
      "val_auroc": 0.7815239425816348,
      "val_f1": 0.728230452674897,
      "best_epoch": 43,
      "lp_epochs_trained": 20,
      "ft_epochs_trained": 63,
      "lp_train_loss": 6.466001464474585,
      "lp_val_acc": 0.6228632478632479
    },
    {
      "fold": 4,
      "train_loss": 2.8066978603601456,
      "val_loss": 1.3017140626907349,
      "val_acc": 0.7627314814814815,
      "val_bal_acc": 0.7627314814814815,
      "val_auroc": 0.8269729509602195,
      "val_f1": 0.762499547445784,
      "best_epoch": 32,
      "lp_epochs_trained": 20,
      "ft_epochs_trained": 52,
      "lp_train_loss": 4.764124438166618,
      "lp_val_acc": 0.625
    },
    {
      "fold": 5,
      "train_loss": 2.759073704481125,
      "val_loss": 1.423723507810522,
      "val_acc": 0.7222222222222222,
      "val_bal_acc": 0.7222222222222222,
      "val_auroc": 0.7963927469135802,
      "val_f1": 0.7216255692069766,
      "best_epoch": 30,
      "lp_epochs_trained": 20,
      "ft_epochs_trained": 50,
      "lp_train_loss": 1.043679853901267,
      "lp_val_acc": 0.6793981481481481
    },
    {
      "fold": 6,
      "train_loss": 2.7774518504738808,
      "val_loss": 1.540364839412548,
      "val_acc": 0.7453703703703703,
      "val_bal_acc": 0.7453703703703705,
      "val_auroc": 0.8069299768518519,
      "val_f1": 0.7440523960078207,
      "best_epoch": 33,
      "lp_epochs_trained": 20,
      "ft_epochs_trained": 53,
      "lp_train_loss": 3.031209245324135,
      "lp_val_acc": 0.6458333333333334
    },
    {
      "fold": 7,
      "train_loss": 2.407328825443983,
      "val_loss": 0.7959270124082212,
      "val_acc": 0.8344907407407407,
      "val_bal_acc": 0.8344907407407407,
      "val_auroc": 0.9021401320301783,
      "val_f1": 0.834426640329024,
      "best_epoch": 45,
      "lp_epochs_trained": 11,
      "ft_epochs_trained": 65,
      "lp_train_loss": 1.3082821778953075,
      "lp_val_acc": 0.5960648148148148
    },
    {
      "fold": 8,
      "train_loss": 2.834967330098152,
      "val_loss": 1.029353424354836,
      "val_acc": 0.7592592592592593,
      "val_bal_acc": 0.7592592592592593,
      "val_auroc": 0.8339897333676269,
      "val_f1": 0.7568502232444866,
      "best_epoch": 22,
      "lp_epochs_trained": 20,
      "ft_epochs_trained": 42,
      "lp_train_loss": 3.028557423502207,
      "lp_val_acc": 0.6458333333333334
    },
    {
      "fold": 9,
      "train_loss": 2.7668850868940353,
      "val_loss": 2.7467956278059216,
      "val_acc": 0.7650462962962963,
      "val_bal_acc": 0.7650462962962963,
      "val_auroc": 0.8142575445816187,
      "val_f1": 0.7647812996627126,
      "best_epoch": 35,
      "lp_epochs_trained": 20,
      "ft_epochs_trained": 55,
      "lp_train_loss": 4.186273287981749,
      "lp_val_acc": 0.6342592592592593
    },
    {
      "fold": 10,
      "train_loss": 2.877890422940254,
      "val_loss": 1.2109189607478954,
      "val_acc": 0.7685185185185185,
      "val_bal_acc": 0.7685185185185186,
      "val_auroc": 0.8336896647805213,
      "val_f1": 0.7685172781489955,
      "best_epoch": 29,
      "lp_epochs_trained": 20,
      "ft_epochs_trained": 49,
      "lp_train_loss": 2.414693271741271,
      "lp_val_acc": 0.6979166666666666
    }
  ],
  "approach": "jade_fullft",
  "lora_rank": 16,
  "supcon_alpha": 0.5,
  "supcon_temperature": 0.03,
  "supcon_repr": "context"
}