{
  "dataset": "faced",
  "task_mode": "binary",
  "completed_at": "2026-04-20T19:04:14.557587",
  "n_folds_run": 10,
  "mean": {
    "train_loss": 3.1793,
    "val_acc": 0.7659,
    "val_bal_acc": 0.7659,
    "val_auroc": 0.8318,
    "val_f1": 0.7653
  },
  "std": {
    "train_loss": 0.3038,
    "val_acc": 0.0266,
    "val_bal_acc": 0.0266,
    "val_auroc": 0.0294,
    "val_f1": 0.0271
  },
  "folds": [
    {
      "fold": 1,
      "train_loss": 3.3636181508341143,
      "val_loss": 2.2206219852480116,
      "val_acc": 0.7660256410256411,
      "val_bal_acc": 0.766025641025641,
      "val_auroc": 0.8446425962451604,
      "val_f1": 0.7638909206093243,
      "best_epoch": 44,
      "lp_epochs_trained": 20,
      "ft_epochs_trained": 64,
      "lp_train_loss": 2.111279147286569,
      "lp_val_acc": 0.6784188034188035
    },
    {
      "fold": 2,
      "train_loss": 3.3603040518299228,
      "val_loss": 1.7108027833139794,
      "val_acc": 0.7649572649572649,
      "val_bal_acc": 0.7649572649572649,
      "val_auroc": 0.8530571992110454,
      "val_f1": 0.7644367163905921,
      "best_epoch": 38,
      "lp_epochs_trained": 20,
      "ft_epochs_trained": 58,
      "lp_train_loss": 2.584838672991722,
      "lp_val_acc": 0.6688034188034188
    },
    {
      "fold": 3,
      "train_loss": 2.908678312455454,
      "val_loss": 3.4827071621886687,
      "val_acc": 0.7574786324786325,
      "val_bal_acc": 0.7574786324786325,
      "val_auroc": 0.8162393162393162,
      "val_f1": 0.7573321059382091,
      "best_epoch": 72,
      "lp_epochs_trained": 20,
      "ft_epochs_trained": 92,
      "lp_train_loss": 2.4449645963407334,
      "lp_val_acc": 0.6720085470085471
    },
    {
      "fold": 4,
      "train_loss": 2.910618782043457,
      "val_loss": 1.107985712863781,
      "val_acc": 0.8194444444444444,
      "val_bal_acc": 0.8194444444444444,
      "val_auroc": 0.8912063828875172,
      "val_f1": 0.8194434769562166,
      "best_epoch": 50,
      "lp_epochs_trained": 12,
      "ft_epochs_trained": 70,
      "lp_train_loss": 4.805137338146331,
      "lp_val_acc": 0.6203703703703703
    },
    {
      "fold": 5,
      "train_loss": 3.723239440766592,
      "val_loss": 1.846942318810357,
      "val_acc": 0.7141203703703703,
      "val_bal_acc": 0.7141203703703703,
      "val_auroc": 0.7907905735596709,
      "val_f1": 0.7119498536182413,
      "best_epoch": 1,
      "lp_epochs_trained": 20,
      "ft_epochs_trained": 21,
      "lp_train_loss": 2.79579112075624,
      "lp_val_acc": 0.6550925925925926
    },
    {
      "fold": 6,
      "train_loss": 3.3914337158203125,
      "val_loss": 1.7421595078927499,
      "val_acc": 0.7673611111111112,
      "val_bal_acc": 0.7673611111111112,
      "val_auroc": 0.8253386488340193,
      "val_f1": 0.7673533198208637,
      "best_epoch": 31,
      "lp_epochs_trained": 20,
      "ft_epochs_trained": 51,
      "lp_train_loss": 1.4668627352941603,
      "lp_val_acc": 0.6944444444444444
    },
    {
      "fold": 7,
      "train_loss": 2.907262499370272,
      "val_loss": 2.2364111917990224,
      "val_acc": 0.7673611111111112,
      "val_bal_acc": 0.7673611111111112,
      "val_auroc": 0.8280499828532236,
      "val_f1": 0.7671661721665006,
      "best_epoch": 81,
      "lp_epochs_trained": 20,
      "ft_epochs_trained": 101,
      "lp_train_loss": 2.58363277760763,
      "lp_val_acc": 0.7129629629629629
    },
    {
      "fold": 8,
      "train_loss": 2.901954915788439,
      "val_loss": 2.817082749472724,
      "val_acc": 0.7777777777777778,
      "val_bal_acc": 0.7777777777777778,
      "val_auroc": 0.8340647505144033,
      "val_f1": 0.777391304347826,
      "best_epoch": 75,
      "lp_epochs_trained": 20,
      "ft_epochs_trained": 95,
      "lp_train_loss": 2.9654701512957375,
      "lp_val_acc": 0.6921296296296297
    },
    {
      "fold": 9,
      "train_loss": 3.413937114533924,
      "val_loss": 4.673644277784559,
      "val_acc": 0.7453703703703703,
      "val_bal_acc": 0.7453703703703705,
      "val_auroc": 0.7923418209876543,
      "val_f1": 0.7452051709623975,
      "best_epoch": 21,
      "lp_epochs_trained": 20,
      "ft_epochs_trained": 41,
      "lp_train_loss": 2.166574713729677,
      "lp_val_acc": 0.6828703703703703
    },
    {
      "fold": 10,
      "train_loss": 2.9118869342501204,
      "val_loss": 2.4653540628927724,
      "val_acc": 0.7789351851851852,
      "val_bal_acc": 0.7789351851851851,
      "val_auroc": 0.8422550154320987,
      "val_f1": 0.7789348890481518,
      "best_epoch": 61,
      "lp_epochs_trained": 20,
      "ft_epochs_trained": 81,
      "lp_train_loss": 1.9007202945058308,
      "lp_val_acc": 0.6979166666666666
    }
  ],
  "approach": "jade_fullft",
  "lora_rank": 16,
  "supcon_alpha": 0.3,
  "supcon_temperature": 0.2,
  "supcon_repr": "context"
}